urlz/__init__.py
urlz/urlz.py
urlz-0.1.2.dist-info/LICENSE
urlz-0.1.2.dist-info/WHEEL
urlz-0.1.2.dist-info/METADATA
urlz-0.1.2.dist-info/RECORD
