Metadata-Version: 2.1
Name: urlz
Version: 0.1.2
Summary: Simple Pathlib-like usage of URLs
Author-email: Steve Berardi <hello@steveberardi.com>
Classifier: License :: OSI Approved :: MIT License
Classifier: Programming Language :: Python :: 3
Classifier: Programming Language :: Python :: 3.7
Classifier: Programming Language :: Python :: 3.8
Classifier: Programming Language :: Python :: 3.9
Classifier: Programming Language :: Python :: 3.10
Classifier: Programming Language :: Python :: 3.11
Project-URL: Home, https://github.com/steveberardi/urlz
